jupyter_cv_utils/__init__.py
jupyter_cv_utils/jupyter_cv_utils.py
jupyter_cv_utils-0.1.0.dist-info/LICENSE
jupyter_cv_utils-0.1.0.dist-info/METADATA
jupyter_cv_utils-0.1.0.dist-info/WHEEL
jupyter_cv_utils-0.1.0.dist-info/top_level.txt
jupyter_cv_utils-0.1.0.dist-info/RECORD
