Metadata-Version: 2.1
Name: jupyter-cv-utils
Version: 0.1.0
Summary: Utility functions to make life easy on Jupyter notebooks.
Home-page: https://github.com/saratrajput/jupyter_cv_utils
Author: Suraj Pattar
Author-email: pattarsuraj@gmail.com
License: UNKNOWN
Platform: UNKNOWN
Classifier: Programming Language :: Python :: 3
Classifier: Programming Language :: Python :: 3.6
Classifier: Programming Language :: Python :: 3.7
Classifier: License :: OSI Approved :: MIT License
Classifier: Operating System :: OS Independent
Requires-Python: >=3.6
License-File: LICENSE
Requires-Dist: opencv-python (>4.0)
Provides-Extra: dev
Requires-Dist: pytest ; extra == 'dev'
